blackwhite/__init__.py
blackwhite/bw.pyd
blackwhite-0.1.7.dist-info/METADATA
blackwhite-0.1.7.dist-info/WHEEL
blackwhite-0.1.7.dist-info/top_level.txt
blackwhite-0.1.7.dist-info/RECORD
