Metadata-Version: 2.1
Name: blackwhite
Version: 0.1.7
Summary: BlackWhite bindings with Python
Author: Vemy
Author-email: chessom@foxmail.com
Platform: Windows
Classifier: Programming Language :: Python :: 3
Classifier: License :: OSI Approved :: MIT License
Classifier: Operating System :: OS Independent
Requires-Python: >=3.10
